setup.py
synapse_pay/APIClient.py
synapse_pay/Clients.py
synapse_pay/Helpers.py
synapse_pay/Node.py
synapse_pay/Nodes.py
synapse_pay/Transaction.py
synapse_pay/Transactions.py
synapse_pay/User.py
synapse_pay/Users.py
synapse_pay/__init__.py
synapse_pay.egg-info/PKG-INFO
synapse_pay.egg-info/SOURCES.txt
synapse_pay.egg-info/dependency_links.txt
synapse_pay.egg-info/requires.txt
synapse_pay.egg-info/top_level.txt