Metadata-Version: 1.1
Name: synapse-pay
Version: 0.0.1
Summary: SynapsePay Python Library
Home-page: https://github.com/synapsepay/SynapsePay-Python
Author: SynapsePay LLC
Author-email: help@synapsepay.com
License: MIT
Keywords: SynapsePay v3 Rest API
Platform: UNKNOWN
Classifier: Development Status :: 3 - Alpha
Classifier: Intended Audience :: Developers
Classifier: License :: OSI Approved :: MIT License
Classifier: Programming Language :: Python :: 2.7
